LICENSE
MANIFEST.in
setup.py
bitlyclip/__init__.py
bitlyclip.egg-info/PKG-INFO
bitlyclip.egg-info/SOURCES.txt
bitlyclip.egg-info/dependency_links.txt
bitlyclip.egg-info/entry_points.txt
bitlyclip.egg-info/not-zip-safe
bitlyclip.egg-info/requires.txt
bitlyclip.egg-info/top_level.txt