Metadata-Version: 1.1
Name: bitlyclip
Version: 0.2.2
Summary: bit.ly-fy a url in the X clipboard
Home-page: http://github.com/ralphbean/bitlyclip
Author: Ralph Bean
Author-email: rbean@redhat.com
License: GPLv3+
Platform: UNKNOWN
Classifier: Development Status :: 4 - Beta
Classifier: Intended Audience :: Developers
Classifier: Intended Audience :: End Users/Desktop
Classifier: License :: OSI Approved :: GNU General Public License (GPL)
Classifier: Programming Language :: Python
Classifier: Programming Language :: Python :: 2.5
Classifier: Programming Language :: Python :: 2.6
Classifier: Programming Language :: Python :: 2.7
Classifier: Topic :: Internet :: WWW/HTTP
Classifier: Topic :: Text Processing :: General
